no_error_python_shell/__init__.py
no_error_python_shell/setup.py
no_error_python_shell.egg-info/PKG-INFO
no_error_python_shell.egg-info/SOURCES.txt
no_error_python_shell.egg-info/dependency_links.txt
no_error_python_shell.egg-info/entry_points.txt
no_error_python_shell.egg-info/top_level.txt