Metadata-Version: 1.0
Name: no-error-python-shell
Version: 0.0.1
Summary: no error python shell
Home-page: https://github.com/theCoder-WM
Author: William Ma
Author-email: 3327821469@qq.com
License: UNKNOWN
Platform: UNKNOWN
